LICENSE
LICENSE.md
README.md
microdata.py
setup.py
microdata.egg-info/PKG-INFO
microdata.egg-info/SOURCES.txt
microdata.egg-info/dependency_links.txt
microdata.egg-info/entry_points.txt
microdata.egg-info/requires.txt
microdata.egg-info/top_level.txt